{
  "id": "pre2-yoji-imi-3",
  "title": "四字熟語（意味）基本3",
  "description": "四字熟語の意味を選ぶ。書きとセットで覚えると得点が伸びる",
  "questions": [
    {
      "id": "yoji-imi-3-01",
      "type": "choice",
      "question": "「竜頭蛇尾」の意味はどれ？",
      "choices": [
        "初めは勢いがさかんで、終わりはふるわないこと",
        "見かけは立派だが中身がないこと",
        "始めから終わりまで勢いがあること",
        "頭と尾でつり合いがとれていること"
      ],
      "answer": 0,
      "hints": ["頭は竜のように立派、尾は蛇のように細い"],
      "explanation": "始まりは竜の頭のように立派でも、終わりは蛇の尾のように細る意。最初だけ威勢がよく尻すぼみになることをいう"
    },
    {
      "id": "yoji-imi-3-02",
      "type": "choice",
      "question": "「有為転変」の意味はどれ？",
      "choices": [
        "この世のすべては移り変わり、はかないこと",
        "才能のある人が活躍すること",
        "状況に応じてうまく立ち回ること",
        "次々と災難が起こること"
      ],
      "answer": 0,
      "hints": ["「有為」は仏教語で、因縁で生じる現象のこと"],
      "explanation": "世の中の物事は常に移り変わってとどまらない、というはかなさをいう。「有為転変は世のならい」と使う"
    },
    {
      "id": "yoji-imi-3-03",
      "type": "choice",
      "question": "「泰山北斗」の意味はどれ？",
      "choices": [
        "その分野で最も尊敬される第一人者",
        "とても大きくて動かないもの",
        "高い山と北の星を望む雄大な景色",
        "人生の目標となる遠い理想"
      ],
      "answer": 0,
      "hints": ["泰山（中国の名山）と北斗星。略して「泰斗」"],
      "explanation": "泰山と北斗星のように、多くの人から仰ぎ尊ばれる権威者・第一人者をいう。「医学界の泰斗」など"
    },
    {
      "id": "yoji-imi-3-04",
      "type": "choice",
      "question": "「金城湯池」の意味はどれ？",
      "choices": [
        "守りが非常にかたく、つけ入るすきのないこと",
        "財産が豊かで栄えていること",
        "美しく豪華な建物のこと",
        "熱意がきわめて高いこと"
      ],
      "answer": 0,
      "hints": ["金の城と、熱湯をたたえた堀（湯池）"],
      "explanation": "鉄壁の城と熱湯の堀の意から、防御がきわめて堅固なたとえ。「金城鉄壁」も同義"
    },
    {
      "id": "yoji-imi-3-05",
      "type": "choice",
      "question": "「合従連衡」の意味はどれ？",
      "choices": [
        "その時の利害に応じて、結びついたり離れたりすること",
        "大勢が力を合わせて一つの目標に進むこと",
        "上下の身分が入れかわること",
        "あちこちを忙しく行き来すること"
      ],
      "answer": 0,
      "hints": ["中国の戦国時代、諸国が同盟を結んだ外交策から"],
      "explanation": "状況次第で同盟や離反をくり返す駆け引きをいう。企業の合併・提携などにも使う"
    },
    {
      "id": "yoji-imi-3-06",
      "type": "choice",
      "question": "「浅学非才」の意味はどれ？",
      "choices": [
        "学問が浅く才能も乏しいこと（多くは謙遜して使う）",
        "学んだことを実生活に生かせないこと",
        "若くして高い学識をもつこと",
        "才能はあるが努力しないこと"
      ],
      "answer": 0,
      "hints": ["自分をへりくだって言うときの定番表現"],
      "explanation": "学識も才能も不十分だという謙遜の言葉。「浅学非才の身ですが」と前置きに使う。「非才」は「菲才」とも書く"
    },
    {
      "id": "yoji-imi-3-07",
      "type": "choice",
      "question": "「比翼連理」の意味はどれ？",
      "choices": [
        "男女の仲がきわめてむつまじいこと",
        "二つの才能を兼ね備えていること",
        "左右が完全につり合っていること",
        "兄弟の仲がよいこと"
      ],
      "answer": 0,
      "hints": ["翼を並べる鳥（比翼の鳥）と、枝が連なる木（連理の枝）"],
      "explanation": "雌雄一体の比翼の鳥と、枝が結びついた連理の枝の意から、夫婦・男女の深い愛情をいう"
    },
    {
      "id": "yoji-imi-3-08",
      "type": "choice",
      "question": "「百鬼夜行」の意味はどれ？",
      "choices": [
        "多くの悪人がはばからず勝手なふるまいをすること",
        "夜中に一人で出歩くこと",
        "おそろしい出来事が次々に起こること",
        "数えきれないほど多いこと"
      ],
      "answer": 0,
      "hints": ["さまざまな化け物が夜に列をなして歩く、という伝承から"],
      "explanation": "多くの妖怪が夜歩く意から、悪人どもが勝手放題に振る舞うことのたとえ。「ひゃっきやぎょう」とも読む"
    }
  ]
}
