{
  "id": "soc-chiri-kinki",
  "title": "近畿地方の特色",
  "description": "近畿地方の地域的特色（教育出版・中学社会 地理）",
  "questions": [
    {
      "id": "q1",
      "type": "choice",
      "question": "滋賀県にある日本最大の湖は？",
      "choices": [
        "琵琶湖",
        "浜名湖",
        "霞ヶ浦",
        "諏訪湖"
      ],
      "answer": 0,
      "answers": [
        "琵琶湖",
        "びわこ",
        "びわ湖"
      ],
      "difficulty": 1,
      "explanation": "①琵琶湖は近畿地方の生活・工業用水を支える「近畿の水がめ」。②琵琶湖から流れ出る水は淀川となって大阪湾へ注ぐ。",
      "hints": [
        "「近畿の水がめ」と呼ばれる湖",
        "び○湖"
      ],
      "concept": "soc-chiri-kinki"
    },
    {
      "id": "q2",
      "type": "input",
      "question": "京都市・奈良市のように、歴史的な街並みを守るため建物の高さやデザインを規制している、古くからの都を何という？",
      "answers": [
        "古都",
        "こと"
      ],
      "placeholder": "○都",
      "difficulty": 2,
      "explanation": "①京都・奈良はかつて都が置かれた古都で、多くの文化財が残る。②景観を守るため看板や建物の高さを制限している（観光資源→保全の取り組み、で押さえる）。",
      "hints": [
        "むかし都だった都市のこと",
        "○都（と）"
      ],
      "concept": "soc-chiri-kinki"
    },
    {
      "id": "q3",
      "type": "choice",
      "question": "大阪を中心に京都・神戸などが連なる大都市圏を何という？",
      "choices": [
        "京阪神（関西）大都市圏",
        "京浜大都市圏",
        "中京大都市圏",
        "北九州大都市圏"
      ],
      "answer": 0,
      "difficulty": 3,
      "explanation": "①近畿地方は大阪を中心に京都・神戸が連なる京阪神（関西）大都市圏を形づくる。②臨海部には中小工場の多い阪神工業地帯が広がる（都市の中心→工業の分布で整理）。",
      "hints": [
        "大阪・京都・神戸の頭文字をつなげた呼び名",
        "京○○大都市圏"
      ],
      "concept": "soc-chiri-kinki"
    },
    {
      "id": "q4",
      "type": "choice",
      "question": "大阪湾沿岸に発達した、中小工場が多いことで知られる工業地帯は？",
      "choices": [
        "阪神工業地帯",
        "中京工業地帯",
        "京浜工業地帯",
        "北九州工業地帯"
      ],
      "answer": 0,
      "answers": [
        "阪神工業地帯",
        "はんしんこうぎょうちたい"
      ],
      "difficulty": 2,
      "explanation": "①阪神工業地帯は大阪・神戸を中心に発達し、金属・化学のほか中小工場が多いのが特徴。②東大阪市などには高い技術をもつ町工場が集まる（地域の特徴を『中小工場』で押さえる）。",
      "hints": [
        "大阪・神戸の頭文字をとった工業地帯",
        "○神工業地帯"
      ],
      "concept": "soc-chiri-kinki"
    },
    {
      "id": "q5",
      "type": "input",
      "question": "降水量が多い紀伊山地（奈良県・三重県）でさかんな、すぎ・ひのきを育てて木材を生産する産業を何という？",
      "answers": [
        "林業",
        "りんぎょう"
      ],
      "placeholder": "○業",
      "difficulty": 2,
      "explanation": "①紀伊山地は雨が多く、すぎ・ひのきがよく育つ。②吉野すぎ・尾鷲ひのきなどのブランド木材を産出する林業がさかん（多雨の気候→森林→林業のつながり）。",
      "hints": [
        "山で木を育てて切り出す産業",
        "吉野すぎ・尾鷲ひのきが有名"
      ],
      "concept": "soc-chiri-kinki"
    },
    {
      "id": "q6",
      "type": "choice",
      "question": "三重県の志摩半島などのリアス海岸の入り江でさかんに行われている養殖は？",
      "choices": [
        "真珠の養殖",
        "こんぶの養殖",
        "ほたての養殖",
        "うなぎの養殖"
      ],
      "answer": 0,
      "answers": [
        "真珠の養殖",
        "真珠",
        "しんじゅ"
      ],
      "difficulty": 2,
      "explanation": "①志摩半島はリアス海岸で、波がおだやかな入り江が多い。②その静かな海を生かしてあこや貝による真珠の養殖が発達した（地形→おだやかな海→養殖の理由）。",
      "hints": [
        "波のおだやかな入り江で育てる、宝石になる貝の産物",
        "あこや貝からとれる"
      ],
      "concept": "soc-chiri-kinki"
    }
  ]
}
