{
  "id": "soc-chiri-shochiiki-cards",
  "title": "西日本の用語カード",
  "description": "用語→説明と説明→用語の両方向で確認する一問一答カード",
  "questions": [
    {
      "id": "c1",
      "type": "flashcard",
      "front": "シラス台地",
      "back": "九州南部に広がる、火山の噴出物が積もってできた台地。\n水持ちが悪く、畑作や畜産が中心"
    },
    {
      "id": "c2",
      "type": "flashcard",
      "front": "促成栽培",
      "back": "ビニールハウスなどで生育を早め、出荷時期を早める栽培方法。\n宮崎平野・高知平野が代表"
    },
    {
      "id": "c3",
      "type": "flashcard",
      "front": "「1901年に操業を開始した、北九州工業地帯のもとになった官営工場」は？",
      "back": "八幡製鉄所。\n日清戦争の賠償金をもとに建設された"
    },
    {
      "id": "c4",
      "type": "flashcard",
      "front": "本州四国連絡橋",
      "back": "本州と四国を結ぶ3つのルートの橋。\n児島・坂出ルート（瀬戸大橋）など"
    },
    {
      "id": "c5",
      "type": "flashcard",
      "front": "ため池",
      "back": "雨の少ない瀬戸内（特に讃岐平野）で、農業用水を確保するためにつくられた池"
    },
    {
      "id": "c6",
      "type": "flashcard",
      "front": "「過疎が進む山間部などで、地域社会の維持が難しくなった集落」を何という？",
      "back": "限界集落。\n65歳以上が半数を超えるなど、共同生活の維持が困難になる"
    },
    {
      "id": "c7",
      "type": "flashcard",
      "front": "地方中枢都市",
      "back": "地方の政治・経済の中心となる都市。\n九州地方の福岡市、中国・四国地方の広島市など"
    },
    {
      "id": "c8",
      "type": "flashcard",
      "front": "瀬戸内工業地域",
      "back": "瀬戸内海沿岸に発達した工業地域。\n石油化学コンビナートが特徴（倉敷・周南など）"
    },
    {
      "id": "c9",
      "type": "flashcard",
      "front": "「愛媛県で生産がさかんな果物」は？",
      "back": "みかん。\n日当たりのよい段々畑で栽培される"
    },
    {
      "id": "c10",
      "type": "flashcard",
      "front": "公害",
      "back": "産業活動などによって環境や健康に被害が出ること。\n四大公害病の水俣病は熊本県で発生した"
    }
  ]
}
