{
  "id": "soc-kindai-cards",
  "title": "日清・日露の用語カード",
  "description": "用語→説明と説明→用語の両方向で確認する一問一答カード",
  "questions": [
    {
      "id": "c1",
      "type": "flashcard",
      "front": "日清戦争",
      "back": "1894年、甲午農民戦争をきっかけに日本と清の間で起こった戦争。\n講和条約は下関条約"
    },
    {
      "id": "c2",
      "type": "flashcard",
      "front": "下関条約",
      "back": "1895年の日清戦争の講和条約。\n清は朝鮮の独立を認め、遼東半島・台湾などを日本にゆずり、賠償金を支払った"
    },
    {
      "id": "c3",
      "type": "flashcard",
      "front": "「ロシア・フランス・ドイツが遼東半島の返還を求めたできごと」は？",
      "back": "三国干渉。\n日本は返還に応じ、ロシアへの対抗心が高まった"
    },
    {
      "id": "c4",
      "type": "flashcard",
      "front": "日英同盟",
      "back": "1902年、ロシアの南下に対抗して日本がイギリスと結んだ同盟"
    },
    {
      "id": "c5",
      "type": "flashcard",
      "front": "日露戦争",
      "back": "1904年に始まった日本とロシアの戦争。\n講和条約はポーツマス条約"
    },
    {
      "id": "c6",
      "type": "flashcard",
      "front": "ポーツマス条約",
      "back": "1905年の日露戦争の講和条約。\n賠償金が得られず、日比谷焼き打ち事件が起こった"
    },
    {
      "id": "c7",
      "type": "flashcard",
      "front": "「1894年に領事裁判権の撤廃に成功した外務大臣」は？",
      "back": "陸奥宗光。\n日清戦争の直前、イギリスとの交渉で実現した"
    },
    {
      "id": "c8",
      "type": "flashcard",
      "front": "「1911年に関税自主権の完全回復に成功した外務大臣」は？",
      "back": "小村寿太郎。\nこれで不平等条約の改正が完了した"
    },
    {
      "id": "c9",
      "type": "flashcard",
      "front": "八幡製鉄所",
      "back": "日清戦争の賠償金をもとに建設され、1901年に操業を開始した官営の製鉄所。\n日本の重工業発展の出発点"
    },
    {
      "id": "c10",
      "type": "flashcard",
      "front": "財閥",
      "back": "三井・三菱など、多くの産業を支配した資本家の一族・企業グループ"
    },
    {
      "id": "c11",
      "type": "flashcard",
      "front": "田中正造",
      "back": "足尾銅山鉱毒事件で、被害者の救済を議会などで訴え続けた人物"
    }
  ]
}
