{
  "id": "tech-i-juu",
  "title": "衣生活・住生活",
  "description": "衣服の手入れ・住まいの安全と快適",
  "questions": [
    {
      "id": "q1",
      "type": "choice",
      "question": "洗濯表示で「液温は40℃を限度・洗濯機で洗える」を表す記号の意味として正しいのは？",
      "choices": [
        "家庭で洗濯機洗いができる",
        "洗濯禁止",
        "ドライクリーニングのみ",
        "手洗いのみ"
      ],
      "answer": 0,
      "answers": [
        "家庭で洗濯機洗いができる"
      ],
      "explanation": "①おけ（洗いおけ）の記号に数字があると、その温度を限度に洗濯機で洗える。②おけに×は洗濯禁止、手の絵は手洗い。記号で扱い方を読み取る。",
      "hints": [
        "「おけ」の記号は洗濯ができるしるし",
        "数字は限度温度"
      ],
      "difficulty": 2
    },
    {
      "id": "q2",
      "type": "choice",
      "question": "衣服の繊維のうち、綿（コットン）の性質として正しいのは？",
      "choices": [
        "吸湿性が高く、肌着に向く",
        "水をはじき乾きにくい",
        "熱に強く燃えない",
        "しわになりにくい"
      ],
      "answer": 0,
      "answers": [
        "吸湿性が高く、肌着に向く"
      ],
      "explanation": "①綿は吸湿性（汗を吸う性質）が高く、肌着やタオルに向く。②しわになりやすい欠点もある。繊維の性質で用途が決まる。",
      "hints": [
        "汗をよく吸う天然繊維",
        "肌着やタオルに使われる"
      ],
      "difficulty": 2
    },
    {
      "id": "q3",
      "type": "choice",
      "question": "アイロンの温度を、繊維に合わせて変えるのはなぜ？",
      "choices": [
        "高温に弱い繊維がこげたり溶けたりするのを防ぐため",
        "色を変えるため",
        "重さを変えるため",
        "理由はない"
      ],
      "answer": 0,
      "answers": [
        "高温に弱い繊維がこげたり溶けたりするのを防ぐため"
      ],
      "explanation": "①化学繊維など熱に弱い繊維は高温でこげたり溶けたりする。②繊維に合った温度にすることで傷めずにしわをのばせる。洗濯表示の点の数が温度の目安。",
      "hints": [
        "熱に弱い繊維がある",
        "こげ・溶けを防ぐため"
      ],
      "difficulty": 1
    },
    {
      "id": "q4",
      "type": "flashcard",
      "front": "まつり縫い",
      "back": "ズボンやスカートのすそ上げに使う、表に縫い目が目立ちにくい手縫いの方法"
    },
    {
      "id": "q5",
      "type": "flashcard",
      "front": "ボタンつけ",
      "back": "布の厚みぶんの「糸足」をつくってからボタンをつけると、とめやすく取れにくい"
    },
    {
      "id": "q6",
      "type": "flashcard",
      "front": "繊維の分類",
      "back": "天然繊維（綿・麻・絹・毛）と化学繊維（ポリエステル・ナイロンなど）に分けられる"
    },
    {
      "id": "q7",
      "type": "choice",
      "question": "住まいで、冬に窓の内側に水滴がつく「結露」の原因は？",
      "choices": [
        "室内の暖かく湿った空気が冷たい窓で冷やされるから",
        "窓から水がしみ出すから",
        "雨がもれているから",
        "換気しすぎるから"
      ],
      "answer": 0,
      "answers": [
        "室内の暖かく湿った空気が冷たい窓で冷やされるから"
      ],
      "explanation": "①暖かく湿った空気が冷たい窓に触れると、含みきれない水蒸気が水滴になる（結露）。②換気や除湿で防げる。理科の露点と同じしくみ。",
      "hints": [
        "暖かく湿った空気＋冷たい窓",
        "理科で習う「露点」と同じしくみ"
      ],
      "difficulty": 3
    },
    {
      "id": "q8",
      "type": "choice",
      "question": "閉めきった部屋で暖房器具を使い続けると危険な「一酸化炭素中毒」を防ぐために大切なことは？",
      "choices": [
        "こまめに換気する",
        "窓を閉めきる",
        "暖房を強くする",
        "加湿する"
      ],
      "answer": 0,
      "answers": [
        "こまめに換気する"
      ],
      "explanation": "①燃焼器具は不完全燃焼で有毒な一酸化炭素を出すことがある。②こまめな換気で新鮮な空気を入れ、中毒を防ぐ。",
      "hints": [
        "新鮮な空気を入れる",
        "窓を開けて空気を入れかえる"
      ],
      "difficulty": 2
    },
    {
      "id": "q9",
      "type": "flashcard",
      "front": "住まいのバリアフリー",
      "back": "段差をなくし手すりをつけるなど、高齢者や体の不自由な人も安全に暮らせる工夫"
    },
    {
      "id": "q10",
      "type": "choice",
      "question": "地震に備えた住まいの安全対策として最も適切なのは？",
      "choices": [
        "家具を壁に固定し、倒れてこないようにする",
        "家具を高く積み上げる",
        "出入り口をふさぐ",
        "重い物を高い所に置く"
      ],
      "answer": 0,
      "answers": [
        "家具を壁に固定し、倒れてこないようにする"
      ],
      "explanation": "①家具の固定で転倒を防ぎ、けがや避難路の確保につなげる。②重い物を高所に置く・出入り口をふさぐのは危険。",
      "hints": [
        "家具を壁に「固定」する",
        "倒れてこない・避難路をふさがない"
      ],
      "difficulty": 1
    }
  ]
}
